LICENSE
MANIFEST.in
README.md
jupyter-materialui.json
setup.cfg
setup.py
ipymaterialui/Events.py
ipymaterialui/Html.py
ipymaterialui/__init__.py
ipymaterialui/_version.py
ipymaterialui.egg-info/PKG-INFO
ipymaterialui.egg-info/SOURCES.txt
ipymaterialui.egg-info/dependency_links.txt
ipymaterialui.egg-info/not-zip-safe
ipymaterialui.egg-info/requires.txt
ipymaterialui.egg-info/top_level.txt
ipymaterialui/generated/AppBar.py
ipymaterialui/generated/Avatar.py
ipymaterialui/generated/Backdrop.py
ipymaterialui/generated/Badge.py
ipymaterialui/generated/BottomNavigation.py
ipymaterialui/generated/BottomNavigationAction.py
ipymaterialui/generated/Breadcrumbs.py
ipymaterialui/generated/Button.py
ipymaterialui/generated/ButtonBase.py
ipymaterialui/generated/ButtonGroup.py
ipymaterialui/generated/Card.py
ipymaterialui/generated/CardActionArea.py
ipymaterialui/generated/CardActions.py
ipymaterialui/generated/CardContent.py
ipymaterialui/generated/CardHeader.py
ipymaterialui/generated/CardMedia.py
ipymaterialui/generated/Checkbox.py
ipymaterialui/generated/Chip.py
ipymaterialui/generated/CircularProgress.py
ipymaterialui/generated/ClickAwayListener.py
ipymaterialui/generated/Collapse.py
ipymaterialui/generated/Container.py
ipymaterialui/generated/CssBaseline.py
ipymaterialui/generated/Dialog.py
ipymaterialui/generated/DialogActions.py
ipymaterialui/generated/DialogContent.py
ipymaterialui/generated/DialogContentText.py
ipymaterialui/generated/DialogTitle.py
ipymaterialui/generated/Divider.py
ipymaterialui/generated/Drawer.py
ipymaterialui/generated/ExpansionPanel.py
ipymaterialui/generated/ExpansionPanelActions.py
ipymaterialui/generated/ExpansionPanelDetails.py
ipymaterialui/generated/ExpansionPanelSummary.py
ipymaterialui/generated/Fab.py
ipymaterialui/generated/Fade.py
ipymaterialui/generated/FilledInput.py
ipymaterialui/generated/FormControl.py
ipymaterialui/generated/FormControlLabel.py
ipymaterialui/generated/FormGroup.py
ipymaterialui/generated/FormHelperText.py
ipymaterialui/generated/FormLabel.py
ipymaterialui/generated/Grid.py
ipymaterialui/generated/GridList.py
ipymaterialui/generated/GridListTile.py
ipymaterialui/generated/GridListTileBar.py
ipymaterialui/generated/Grow.py
