Metadata-Version: 1.1
Name: ipymaterialui
Version: 0.1.4
Summary: Modern form/ui elements for Jupyter Widgets
Home-page: https://github.com/maartenbreddels/ipymaterialui
Author: Maarten A. Breddels, Mario Buikhuizen
Author-email: maartenbreddels@gmail.com, mariobuikhuizen@gmail.com
License: UNKNOWN
Keywords: ipython,jupyter,widgets
Platform: UNKNOWN
Classifier: Development Status :: 4 - Beta
Classifier: Framework :: IPython
Classifier: Intended Audience :: Developers
Classifier: Intended Audience :: Science/Research
Classifier: Topic :: Multimedia :: Graphics
Classifier: Programming Language :: Python :: 2
Classifier: Programming Language :: Python :: 2.7
Classifier: Programming Language :: Python :: 3
Classifier: Programming Language :: Python :: 3.3
Classifier: Programming Language :: Python :: 3.4
Classifier: Programming Language :: Python :: 3.5
